myscipkg2/__init__.py
myscipkg2/tests/__init__.py
myscipkg2/tests/test_myscipkg2.py
myscipkg2-0.1.3.dist-info/DESCRIPTION.rst
myscipkg2-0.1.3.dist-info/METADATA
myscipkg2-0.1.3.dist-info/metadata.json
myscipkg2-0.1.3.dist-info/RECORD
myscipkg2-0.1.3.dist-info/top_level.txt
myscipkg2-0.1.3.dist-info/WHEEL
