Metadata-Version: 2.0
Name: myscipkg2
Version: 0.1.3
Summary: A package for science using numpy, matplotlib, readthedocs, etc.
Home-page: https://github.com/ryanpdwyer/myscipkg2
Author: Ryan Dwyer
Author-email: ryanpdwyer@gmail.com
License: MIT
Keywords: myscipkg2
Platform: UNKNOWN
Classifier: Development Status :: 2 - Pre-Alpha
Classifier: Intended Audience :: Developers
Classifier: License :: OSI Approved :: MIT License
Classifier: Natural Language :: English
Classifier: Programming Language :: Python :: 2
Classifier: Programming Language :: Python :: 2.7
